{
    "name": "Conflict of Interests VANILLA",
    "mapsvg": "assets/worldmap.svg",
    "countries": [
        "content/countries/countries.json"
    ],
    "map": [
        "content/map.json"
    ],
    "people": [
        "content/people/people.json"
    ],
    "decisions": [
        "content/decisions/decisions.json"
    ],
    "events": [
        "content/events/events.json"
    ],
    "on_actions": [
        "content/on_actions.json"
    ],
    "localisation": [
        "localisation/tiles.json",
        "localisation/countries.json",
        "localisation/other.json"
    ],
    "config": "content/config.json"
}